{
  "metadata": {
    "soundFile": "C:\\Users\\Ahmad Afzal\\Desktop\\oddo\\public\\audios\\focus.wav",
    "duration": 8.49
  },
  "mouthCues": [
    { "start": 0.00, "end": 0.10, "value": "X" },
    { "start": 0.10, "end": 0.16, "value": "B" },
    { "start": 0.16, "end": 0.22, "value": "C" },
    { "start": 0.22, "end": 0.30, "value": "A" },
    { "start": 0.30, "end": 0.38, "value": "C" },
    { "start": 0.38, "end": 0.52, "value": "B" },
    { "start": 0.52, "end": 0.59, "value": "G" },
    { "start": 0.59, "end": 0.66, "value": "E" },
    { "start": 0.66, "end": 1.15, "value": "B" },
    { "start": 1.15, "end": 1.22, "value": "F" },
    { "start": 1.22, "end": 1.36, "value": "B" },
    { "start": 1.36, "end": 1.43, "value": "G" },
    { "start": 1.43, "end": 1.57, "value": "B" },
    { "start": 1.57, "end": 1.65, "value": "A" },
    { "start": 1.65, "end": 1.87, "value": "E" },
    { "start": 1.87, "end": 2.08, "value": "F" },
    { "start": 2.08, "end": 2.43, "value": "B" },
    { "start": 2.43, "end": 2.50, "value": "E" },
    { "start": 2.50, "end": 2.71, "value": "C" },
    { "start": 2.71, "end": 2.85, "value": "B" },
    { "start": 2.85, "end": 2.92, "value": "F" },
    { "start": 2.92, "end": 2.99, "value": "D" },
    { "start": 2.99, "end": 3.20, "value": "B" },
    { "start": 3.20, "end": 3.34, "value": "C" },
    { "start": 3.34, "end": 3.48, "value": "B" },
    { "start": 3.48, "end": 3.56, "value": "A" },
    { "start": 3.56, "end": 3.78, "value": "C" },
    { "start": 3.78, "end": 3.85, "value": "B" },
    { "start": 3.85, "end": 3.99, "value": "E" },
    { "start": 3.99, "end": 4.48, "value": "B" },
    { "start": 4.48, "end": 4.55, "value": "C" },
    { "start": 4.55, "end": 4.62, "value": "G" },
    { "start": 4.62, "end": 4.69, "value": "E" },
    { "start": 4.69, "end": 4.90, "value": "B" },
    { "start": 4.90, "end": 4.97, "value": "C" },
    { "start": 4.97, "end": 5.04, "value": "B" },
    { "start": 5.04, "end": 5.12, "value": "A" },
    { "start": 5.12, "end": 5.19, "value": "B" },
    { "start": 5.19, "end": 5.26, "value": "C" },
    { "start": 5.26, "end": 5.33, "value": "G" },
    { "start": 5.33, "end": 5.40, "value": "C" },
    { "start": 5.40, "end": 5.47, "value": "B" },
    { "start": 5.47, "end": 5.61, "value": "C" },
    { "start": 5.61, "end": 5.82, "value": "B" },
    { "start": 5.82, "end": 5.89, "value": "C" },
    { "start": 5.89, "end": 6.16, "value": "A" },
    { "start": 6.16, "end": 6.21, "value": "C" },
    { "start": 6.21, "end": 6.26, "value": "B" },
    { "start": 6.26, "end": 6.34, "value": "A" },
    { "start": 6.34, "end": 6.44, "value": "E" },
    { "start": 6.44, "end": 7.07, "value": "B" },
    { "start": 7.07, "end": 7.35, "value": "C" },
    { "start": 7.35, "end": 7.49, "value": "B" },
    { "start": 7.49, "end": 7.57, "value": "A" },
    { "start": 7.57, "end": 7.75, "value": "B" },
    { "start": 7.75, "end": 7.82, "value": "C" },
    { "start": 7.82, "end": 8.03, "value": "B" },
    { "start": 8.03, "end": 8.17, "value": "C" },
    { "start": 8.17, "end": 8.31, "value": "B" },
    { "start": 8.31, "end": 8.45, "value": "C" },
    { "start": 8.45, "end": 8.49, "value": "X" }
  ]
}
